sublinput/__init__.py
sublinput/ui.py
sublinput-1.0.1.dist-info/METADATA
sublinput-1.0.1.dist-info/WHEEL
sublinput-1.0.1.dist-info/top_level.txt
sublinput-1.0.1.dist-info/RECORD
