Metadata-Version: 2.1
Name: sublinput
Version: 1.0.1
Summary: An input pygame alternative for sublime text users.
Home-page: https://github.com/Sigmanificient/pg-sublime-input
Author: Sigmanificient
Author-email: Edhyjox@gmail.com
License: MIT
Platform: UNKNOWN
Classifier: License :: OSI Approved :: MIT License
Classifier: Programming Language :: Python :: 3.6
Classifier: Programming Language :: Python :: 3.7
Classifier: Programming Language :: Python :: 3.8
Requires-Dist: pygame
